README.rst
setup.cfg
setup.py
vtools/__init__.py
vtools/colors.py
vtools/config.py
vtools/types.py
vtools/vcontours.py
vtools/vhist.py
vtools/vimg.py
vtools/vplot.py
vtools/vtools.py
vtools.egg-info/PKG-INFO
vtools.egg-info/SOURCES.txt
vtools.egg-info/dependency_links.txt
vtools.egg-info/not-zip-safe
vtools.egg-info/requires.txt
vtools.egg-info/top_level.txt