Metadata-Version: 1.1
Name: vtools
Version: 0.0.35
Summary: Visual Tools - an object oriented approach to image processing and analysis.
Home-page: https://github.com/etherwar/vtools
Author: Vic Jackson
Author-email: mr.vic.jackson@gmail.com
License: MIT
Download-URL: https://github.com/etherwar/vtools/archive/master.zip
Keywords: vtools,vimg,OpenCV,image analysis,contours,computer,vision,visual,contour,analysis,image,processing,image,processing,OO,Object,Oriented
Platform: UNKNOWN
